pluralizer/__init__.py
pluralizer/pluralizer.py
pluralizer/pluralizer_rules.py
pluralizer-1.1.0.dist-info/LICENSE
pluralizer-1.1.0.dist-info/METADATA
pluralizer-1.1.0.dist-info/WHEEL
pluralizer-1.1.0.dist-info/top_level.txt
pluralizer-1.1.0.dist-info/RECORD
