Metadata-Version: 2.1
Name: pluralizer
Version: 1.1.0
Summary: Singularize or pluralize a given word useing a pre-defined list of rules
Home-page: https://github.com/weixu365/pluralizer-py
Author: Wei Xu
License: MIT
Keywords: pluralize,singularize,singular,plural
Platform: any
Classifier: Development Status :: 5 - Production/Stable
Classifier: Intended Audience :: Developers
Classifier: Topic :: Software Development :: Libraries :: Python Modules
Classifier: License :: OSI Approved :: MIT License
Classifier: Programming Language :: Python :: 3
Classifier: Programming Language :: Python :: 3.6
Requires-Python: >=3.6
